my_package_test181097/__init__.py
my_package_test181097-0.1.0.dist-info/METADATA
my_package_test181097-0.1.0.dist-info/WHEEL
my_package_test181097-0.1.0.dist-info/RECORD
