Metadata-Version: 2.1
Name: my-package-test181097
Version: 0.1.0
Summary: 
Author: tin-coin98
Author-email: tinnt@coin98.finance
Requires-Python: >=3.12,<4.0
Classifier: Programming Language :: Python :: 3
Classifier: Programming Language :: Python :: 3.12
Requires-Dist: requests (>=2.31.0,<3.0.0)
